{
  "humidity": 97.0,
  "dew": 24.67,
  "temp": 25.38,
  "windDir": 112.32,
  "windSpeed": 4.08,
  "pressure": 1000.4,
  "coreTrigger": {},
  "confidence": "high",
  "intensity": {},
  "updatedAt": "2026-06-27T03:05:02.329946",
  "raw_sources": {
    "qweather": {
      "temp": 25.2,
      "humidity": 97.0,
      "dew": 24.4,
      "windDir": 75.6,
      "windSpeed": 5.1,
      "pressure": 998.6
    },
    "openmeteo": {
      "temp": 25.8,
      "humidity": 97,
      "dew": 25.3,
      "windDir": 198,
      "windSpeed": 1.7,
      "pressure": 1004.6
    }
  },
  "source_diff": {
    "temp": -0.6,
    "humidity": 0.0,
    "dew": -0.9,
    "windDir": -122.4,
    "windSpeed": 3.4,
    "pressure": -6.0
  }
}